{
  "$schema": "https://raw.githubusercontent.com/spdx/spdx-spec/v2.2.1/schemas/spdx-schema.json",
  "spdxVersion": "SPDX-2.2",
  "dataLicense": "CC0-1.0",
  "SPDXID": "SPDXRef-DOCUMENT",
  "documentNamespace": "https://spdx.org/spdxdocs/boost-program-options-x64-linux-1.82.0#1-f014aa87-608f-4097-afb5-61f1536633a4",
  "name": "boost-program-options:x64-linux@1.82.0#1 7258b8f39066dfa412701dcd6b217f8e165162dd36729886cb91aa2bcca4a0eb",
  "creationInfo": {
    "creators": [
      "Tool: vcpkg-bedcba5172f5e4b91caac660ab7afe92c27a9895"
    ],
    "created": "2023-05-17T16:29:45Z"
  },
  "relationships": [
    {
      "spdxElementId": "SPDXRef-port",
      "relationshipType": "GENERATES",
      "relatedSpdxElement": "SPDXRef-binary"
    },
    {
      "spdxElementId": "SPDXRef-port",
      "relationshipType": "CONTAINS",
      "relatedSpdxElement": "SPDXRef-file-0"
    },
    {
      "spdxElementId": "SPDXRef-port",
      "relationshipType": "CONTAINS",
      "relatedSpdxElement": "SPDXRef-file-1"
    },
    {
      "spdxElementId": "SPDXRef-binary",
      "relationshipType": "GENERATED_FROM",
      "relatedSpdxElement": "SPDXRef-port"
    },
    {
      "spdxElementId": "SPDXRef-file-0",
      "relationshipType": "CONTAINED_BY",
      "relatedSpdxElement": "SPDXRef-port"
    },
    {
      "spdxElementId": "SPDXRef-file-1",
      "relationshipType": "CONTAINED_BY",
      "relatedSpdxElement": "SPDXRef-port"
    },
    {
      "spdxElementId": "SPDXRef-file-1",
      "relationshipType": "DEPENDENCY_MANIFEST_OF",
      "relatedSpdxElement": "SPDXRef-port"
    }
  ],
  "packages": [
    {
      "name": "boost-program-options",
      "SPDXID": "SPDXRef-port",
      "versionInfo": "1.82.0#1",
      "downloadLocation": "NOASSERTION",
      "homepage": "https://github.com/boostorg/program_options",
      "licenseConcluded": "BSL-1.0",
      "licenseDeclared": "NOASSERTION",
      "copyrightText": "NOASSERTION",
      "description": "Boost program_options module",
      "comment": "This is the port (recipe) consumed by vcpkg."
    },
    {
      "name": "boost-program-options:x64-linux",
      "SPDXID": "SPDXRef-binary",
      "versionInfo": "7258b8f39066dfa412701dcd6b217f8e165162dd36729886cb91aa2bcca4a0eb",
      "downloadLocation": "NONE",
      "licenseConcluded": "BSL-1.0",
      "licenseDeclared": "NOASSERTION",
      "copyrightText": "NOASSERTION",
      "comment": "This is a binary package built by vcpkg."
    },
    {
      "SPDXID": "SPDXRef-resource-1",
      "name": "boostorg/program_options",
      "downloadLocation": "git+https://github.com/boostorg/program_options@boost-1.82.0",
      "licenseConcluded": "NOASSERTION",
      "licenseDeclared": "NOASSERTION",
      "copyrightText": "NOASSERTION",
      "checksums": [
        {
          "algorithm": "SHA512",
          "checksumValue": "4b7c27cebc1637e3dcd0a2a7fd09f5793409f8900c545b4b504d14f6448cb01f90e80885654259360a96f0da63c23a2972347b6be1151b8679f9acb4d56b88ef"
        }
      ]
    }
  ],
  "files": [
    {
      "fileName": "./portfile.cmake",
      "SPDXID": "SPDXRef-file-0",
      "checksums": [
        {
          "algorithm": "SHA256",
          "checksumValue": "641d71a0b7e1def438b12f26a776ca262a12dfebd40b71d8312d2c925093dd07"
        }
      ],
      "licenseConcluded": "NOASSERTION",
      "copyrightText": "NOASSERTION"
    },
    {
      "fileName": "./vcpkg.json",
      "SPDXID": "SPDXRef-file-1",
      "checksums": [
        {
          "algorithm": "SHA256",
          "checksumValue": "8ae21c208e52187b7d776e43f48547a98a77a785aa70711dee1b2e41bb3ef1cd"
        }
      ],
      "licenseConcluded": "NOASSERTION",
      "copyrightText": "NOASSERTION"
    }
  ]
}
