{
  "$schema": "https://raw.githubusercontent.com/spdx/spdx-spec/v2.2.1/schemas/spdx-schema.json",
  "spdxVersion": "SPDX-2.2",
  "dataLicense": "CC0-1.0",
  "SPDXID": "SPDXRef-DOCUMENT",
  "documentNamespace": "https://spdx.org/spdxdocs/boost-optional-x64-linux-1.82.0#1-807c1030-a268-48f4-8ab4-1252fdc3a811",
  "name": "boost-optional:x64-linux@1.82.0#1 fcb95b2d8ae99d5e8b9fffe268f25e23042e622d310573a67c42b7894a29b2e0",
  "creationInfo": {
    "creators": [
      "Tool: vcpkg-12e657924d99511514c0287ca5ce46882d3657c7"
    ],
    "created": "2023-04-28T18:35:27Z"
  },
  "relationships": [
    {
      "spdxElementId": "SPDXRef-port",
      "relationshipType": "GENERATES",
      "relatedSpdxElement": "SPDXRef-binary"
    },
    {
      "spdxElementId": "SPDXRef-port",
      "relationshipType": "CONTAINS",
      "relatedSpdxElement": "SPDXRef-file-0"
    },
    {
      "spdxElementId": "SPDXRef-port",
      "relationshipType": "CONTAINS",
      "relatedSpdxElement": "SPDXRef-file-1"
    },
    {
      "spdxElementId": "SPDXRef-binary",
      "relationshipType": "GENERATED_FROM",
      "relatedSpdxElement": "SPDXRef-port"
    },
    {
      "spdxElementId": "SPDXRef-file-0",
      "relationshipType": "CONTAINED_BY",
      "relatedSpdxElement": "SPDXRef-port"
    },
    {
      "spdxElementId": "SPDXRef-file-1",
      "relationshipType": "CONTAINED_BY",
      "relatedSpdxElement": "SPDXRef-port"
    },
    {
      "spdxElementId": "SPDXRef-file-1",
      "relationshipType": "DEPENDENCY_MANIFEST_OF",
      "relatedSpdxElement": "SPDXRef-port"
    }
  ],
  "packages": [
    {
      "name": "boost-optional",
      "SPDXID": "SPDXRef-port",
      "versionInfo": "1.82.0#1",
      "downloadLocation": "NOASSERTION",
      "homepage": "https://github.com/boostorg/optional",
      "licenseConcluded": "BSL-1.0",
      "licenseDeclared": "NOASSERTION",
      "copyrightText": "NOASSERTION",
      "description": "Boost optional module",
      "comment": "This is the port (recipe) consumed by vcpkg."
    },
    {
      "name": "boost-optional:x64-linux",
      "SPDXID": "SPDXRef-binary",
      "versionInfo": "fcb95b2d8ae99d5e8b9fffe268f25e23042e622d310573a67c42b7894a29b2e0",
      "downloadLocation": "NONE",
      "licenseConcluded": "BSL-1.0",
      "licenseDeclared": "NOASSERTION",
      "copyrightText": "NOASSERTION",
      "comment": "This is a binary package built by vcpkg."
    },
    {
      "SPDXID": "SPDXRef-resource-1",
      "name": "boostorg/optional",
      "downloadLocation": "git+https://github.com/boostorg/optional@boost-1.82.0",
      "licenseConcluded": "NOASSERTION",
      "licenseDeclared": "NOASSERTION",
      "copyrightText": "NOASSERTION",
      "checksums": [
        {
          "algorithm": "SHA512",
          "checksumValue": "5439e9a1ecd2e74e7f9dfb958989edc0a68f0a9275fb8d472fcb32b6b8d120c9eb26e92a345485e0bb04950606cc065a9bfdf6a4cfc28602a5bcc8e13629e934"
        }
      ]
    }
  ],
  "files": [
    {
      "fileName": "./portfile.cmake",
      "SPDXID": "SPDXRef-file-0",
      "checksums": [
        {
          "algorithm": "SHA256",
          "checksumValue": "c9af13ec626fe68ff7ced398e554f8ebc1ba5b1522eaaaeda21dc2b535434cd0"
        }
      ],
      "licenseConcluded": "NOASSERTION",
      "copyrightText": "NOASSERTION"
    },
    {
      "fileName": "./vcpkg.json",
      "SPDXID": "SPDXRef-file-1",
      "checksums": [
        {
          "algorithm": "SHA256",
          "checksumValue": "efe3c4b2c26f67af6a02cf2b9ce0997cba594d5500ef47bb876160f1aaa08954"
        }
      ],
      "licenseConcluded": "NOASSERTION",
      "copyrightText": "NOASSERTION"
    }
  ]
}
