{
  "$schema": "https://raw.githubusercontent.com/spdx/spdx-spec/v2.2.1/schemas/spdx-schema.json",
  "spdxVersion": "SPDX-2.2",
  "dataLicense": "CC0-1.0",
  "SPDXID": "SPDXRef-DOCUMENT",
  "documentNamespace": "https://spdx.org/spdxdocs/boost-lambda-x64-linux-1.82.0#1-fc6c5ffc-4a9f-4bea-a3db-cd14872536fc",
  "name": "boost-lambda:x64-linux@1.82.0#1 b617ba7935db5e580cdca8050659ec8dda0a36618eeea33588de3a774e0e8112",
  "creationInfo": {
    "creators": [
      "Tool: vcpkg-bedcba5172f5e4b91caac660ab7afe92c27a9895"
    ],
    "created": "2023-05-17T16:17:40Z"
  },
  "relationships": [
    {
      "spdxElementId": "SPDXRef-port",
      "relationshipType": "GENERATES",
      "relatedSpdxElement": "SPDXRef-binary"
    },
    {
      "spdxElementId": "SPDXRef-port",
      "relationshipType": "CONTAINS",
      "relatedSpdxElement": "SPDXRef-file-0"
    },
    {
      "spdxElementId": "SPDXRef-port",
      "relationshipType": "CONTAINS",
      "relatedSpdxElement": "SPDXRef-file-1"
    },
    {
      "spdxElementId": "SPDXRef-binary",
      "relationshipType": "GENERATED_FROM",
      "relatedSpdxElement": "SPDXRef-port"
    },
    {
      "spdxElementId": "SPDXRef-file-0",
      "relationshipType": "CONTAINED_BY",
      "relatedSpdxElement": "SPDXRef-port"
    },
    {
      "spdxElementId": "SPDXRef-file-1",
      "relationshipType": "CONTAINED_BY",
      "relatedSpdxElement": "SPDXRef-port"
    },
    {
      "spdxElementId": "SPDXRef-file-1",
      "relationshipType": "DEPENDENCY_MANIFEST_OF",
      "relatedSpdxElement": "SPDXRef-port"
    }
  ],
  "packages": [
    {
      "name": "boost-lambda",
      "SPDXID": "SPDXRef-port",
      "versionInfo": "1.82.0#1",
      "downloadLocation": "NOASSERTION",
      "homepage": "https://github.com/boostorg/lambda",
      "licenseConcluded": "BSL-1.0",
      "licenseDeclared": "NOASSERTION",
      "copyrightText": "NOASSERTION",
      "description": "Boost lambda module",
      "comment": "This is the port (recipe) consumed by vcpkg."
    },
    {
      "name": "boost-lambda:x64-linux",
      "SPDXID": "SPDXRef-binary",
      "versionInfo": "b617ba7935db5e580cdca8050659ec8dda0a36618eeea33588de3a774e0e8112",
      "downloadLocation": "NONE",
      "licenseConcluded": "BSL-1.0",
      "licenseDeclared": "NOASSERTION",
      "copyrightText": "NOASSERTION",
      "comment": "This is a binary package built by vcpkg."
    },
    {
      "SPDXID": "SPDXRef-resource-1",
      "name": "boostorg/lambda",
      "downloadLocation": "git+https://github.com/boostorg/lambda@boost-1.82.0",
      "licenseConcluded": "NOASSERTION",
      "licenseDeclared": "NOASSERTION",
      "copyrightText": "NOASSERTION",
      "checksums": [
        {
          "algorithm": "SHA512",
          "checksumValue": "77aca9157d9784d0ba3dc4614027c0e411bcf035715f049815b4a27063fd8878477b5ce472bc063db7dd887773ff17164d19d5aede4b3d06365d6c427acc4555"
        }
      ]
    }
  ],
  "files": [
    {
      "fileName": "./portfile.cmake",
      "SPDXID": "SPDXRef-file-0",
      "checksums": [
        {
          "algorithm": "SHA256",
          "checksumValue": "b3db9cd161dee2da8e426eb89f93010402a976fd1b89539f7044e4269198c613"
        }
      ],
      "licenseConcluded": "NOASSERTION",
      "copyrightText": "NOASSERTION"
    },
    {
      "fileName": "./vcpkg.json",
      "SPDXID": "SPDXRef-file-1",
      "checksums": [
        {
          "algorithm": "SHA256",
          "checksumValue": "62268b880036ff3b86c85c9685a26901b15e645d9c85a9120a89bc7a90192510"
        }
      ],
      "licenseConcluded": "NOASSERTION",
      "copyrightText": "NOASSERTION"
    }
  ]
}
